Workbook

Sheet 模板
C1: 销售订单
C2: 需求方（甲方）： | E2: 首品团（专票）
C3: 供货方（乙方）： | E3: 广州启航化妆品科技有限公司 | H3: 订单日期： | I3: 2026/5/1-2026/5/31
H4: 运费承担方式： | I4: 需方承担
C5: 1、产品名称、规格及型号、数量、单价、数量：
C6: 序号 | D6: 产品名称 | F6: 单位 | G6: 数量 | H6: 单价（人民币） | I6: 金额（元） | J6: 备注
B7: =IF(ROW(A1)>MAX(订单!$B:$B),"",ROW(A1)) | C7: 1 | D7: =IFERROR(IF($B7="","",VLOOKUP($B7,订单!$B$2:$J$29583,3,FALSE)),"") | F7: =IFERROR(IF($B7="","",VLOOKUP($B7,订单!$B$2:$J$29589,MATCH(F$6,订单!$B$1:$I$1,0),FALSE)),"") | G7: =IFERROR(IF($B7="","",VLOOKUP($B7,订单!$B$2:$J$29589,MATCH(G$6,订单!$B$1:$I$1,0),FALSE)),"") | H7: =IFERROR(IF($B7="","",VLOOKUP($B7,订单!$B$2:$J$29589,MATCH(H$6,订单!$B$1:$I$1,0),FALSE)),"") | I7: =IFERROR(IF($B7="","",VLOOKUP($B7,订单!$B$2:$J$29589,MATCH(I$6,订单!$B$1:$I$1,0),FALSE)),"") | J7: =IFERROR(IF($B7="","",VLOOKUP($B7,订单!$B$2:$J$29589,MATCH(J$6,订单!$B$1:$I$1,0),FALSE)),"")
B8: =IF(ROW(A2)>MAX(订单!$B:$B),"",ROW(A2)) | C8: =ROW()-6 | D8: =IFERROR(IF($B8="","",VLOOKUP($B8,订单!$B$2:$J$29583,3,FALSE)),"") | F8: =IFERROR(IF($B8="","",VLOOKUP($B8,订单!$B$2:$J$29589,MATCH(F$6,订单!$B$1:$I$1,0),FALSE)),"") | G8: =IFERROR(IF($B8="","",VLOOKUP($B8,订单!$B$2:$J$29589,MATCH(G$6,订单!$B$1:$I$1,0),FALSE)),"") | H8: =IFERROR(IF($B8="","",VLOOKUP($B8,订单!$B$2:$J$29589,MATCH(H$6,订单!$B$1:$I$1,0),FALSE)),"") | I8: =IFERROR(IF($B8="","",VLOOKUP($B8,订单!$B$2:$J$29589,MATCH(I$6,订单!$B$1:$I$1,0),FALSE)),"") | J8: =IFERROR(IF($B8="","",VLOOKUP($B8,订单!$B$2:$J$29589,MATCH(J$6,订单!$B$1:$I$1,0),FALSE)),"")
B9: =IF(ROW(A3)>MAX(订单!$B:$B),"",ROW(A3)) | C9: =ROW()-6 | D9: =IFERROR(IF($B9="","",VLOOKUP($B9,订单!$B$2:$J$29583,3,FALSE)),"") | F9: =IFERROR(IF($B9="","",VLOOKUP($B9,订单!$B$2:$J$29589,MATCH(F$6,订单!$B$1:$I$1,0),FALSE)),"") | G9: =IFERROR(IF($B9="","",VLOOKUP($B9,订单!$B$2:$J$29589,MATCH(G$6,订单!$B$1:$I$1,0),FALSE)),"") | H9: =IFERROR(IF($B9="","",VLOOKUP($B9,订单!$B$2:$J$29589,MATCH(H$6,订单!$B$1:$I$1,0),FALSE)),"") | I9: =IFERROR(IF($B9="","",VLOOKUP($B9,订单!$B$2:$J$29589,MATCH(I$6,订单!$B$1:$I$1,0),FALSE)),"") | J9: =IFERROR(IF($B9="","",VLOOKUP($B9,订单!$B$2:$J$29589,MATCH(J$6,订单!$B$1:$I$1,0),FALSE)),"")
B10: =IF(ROW(A4)>MAX(订单!$B:$B),"",ROW(A4)) | C10: =ROW()-6 | D10: =IFERROR(IF($B10="","",VLOOKUP($B10,订单!$B$2:$J$29583,3,FALSE)),"") | F10: =IFERROR(IF($B10="","",VLOOKUP($B10,订单!$B$2:$J$29589,MATCH(F$6,订单!$B$1:$I$1,0),FALSE)),"") | G10: =IFERROR(IF($B10="","",VLOOKUP($B10,订单!$B$2:$J$29589,MATCH(G$6,订单!$B$1:$I$1,0),FALSE)),"") | H10: =IFERROR(IF($B10="","",VLOOKUP($B10,订单!$B$2:$J$29589,MATCH(H$6,订单!$B$1:$I$1,0),FALSE)),"") | I10: =IFERROR(IF($B10="","",VLOOKUP($B10,订单!$B$2:$J$29589,MATCH(I$6,订单!$B$1:$I$1,0),FALSE)),"") | J10: =IFERROR(IF($B10="","",VLOOKUP($B10,订单!$B$2:$J$29589,MATCH(J$6,订单!$B$1:$I$1,0),FALSE)),"")
B11: =IF(ROW(A5)>MAX(订单!$B:$B),"",ROW(A5)) | C11: =ROW()-6 | D11: =IFERROR(IF($B11="","",VLOOKUP($B11,订单!$B$2:$J$29583,3,FALSE)),"") | F11: =IFERROR(IF($B11="","",VLOOKUP($B11,订单!$B$2:$J$29589,MATCH(F$6,订单!$B$1:$I$1,0),FALSE)),"") | G11: =IFERROR(IF($B11="","",VLOOKUP($B11,订单!$B$2:$J$29589,MATCH(G$6,订单!$B$1:$I$1,0),FALSE)),"") | H11: =IFERROR(IF($B11="","",VLOOKUP($B11,订单!$B$2:$J$29589,MATCH(H$6,订单!$B$1:$I$1,0),FALSE)),"") | I11: =IFERROR(IF($B11="","",VLOOKUP($B11,订单!$B$2:$J$29589,MATCH(I$6,订单!$B$1:$I$1,0),FALSE)),"") | J11: =IFERROR(IF($B11="","",VLOOKUP($B11,订单!$B$2:$J$29589,MATCH(J$6,订单!$B$1:$I$1,0),FALSE)),"")
B12: =IF(ROW(A6)>MAX(订单!$B:$B),"",ROW(A6)) | C12: =ROW()-6 | D12: =IFERROR(IF($B12="","",VLOOKUP($B12,订单!$B$2:$J$29583,3,FALSE)),"") | F12: =IFERROR(IF($B12="","",VLOOKUP($B12,订单!$B$2:$J$29589,MATCH(F$6,订单!$B$1:$I$1,0),FALSE)),"") | G12: =IFERROR(IF($B12="","",VLOOKUP($B12,订单!$B$2:$J$29589,MATCH(G$6,订单!$B$1:$I$1,0),FALSE)),"") | H12: =IFERROR(IF($B12="","",VLOOKUP($B12,订单!$B$2:$J$29589,MATCH(H$6,订单!$B$1:$I$1,0),FALSE)),"") | I12: =IFERROR(IF($B12="","",VLOOKUP($B12,订单!$B$2:$J$29589,MATCH(I$6,订单!$B$1:$I$1,0),FALSE)),"") | J12: =IFERROR(IF($B12="","",VLOOKUP($B12,订单!$B$2:$J$29589,MATCH(J$6,订单!$B$1:$I$1,0),FALSE)),"")
B13: =IF(ROW(A7)>MAX(订单!$B:$B),"",ROW(A7)) | C13: =ROW()-6 | D13: =IFERROR(IF($B13="","",VLOOKUP($B13,订单!$B$2:$J$29583,3,FALSE)),"") | F13: =IFERROR(IF($B13="","",VLOOKUP($B13,订单!$B$2:$J$29589,MATCH(F$6,订单!$B$1:$I$1,0),FALSE)),"") | G13: =IFERROR(IF($B13="","",VLOOKUP($B13,订单!$B$2:$J$29589,MATCH(G$6,订单!$B$1:$I$1,0),FALSE)),"") | H13: =IFERROR(IF($B13="","",VLOOKUP($B13,订单!$B$2:$J$29589,MATCH(H$6,订单!$B$1:$I$1,0),FALSE)),"") | I13: =IFERROR(IF($B13="","",VLOOKUP($B13,订单!$B$2:$J$29589,MATCH(I$6,订单!$B$1:$I$1,0),FALSE)),"") | J13: =IFERROR(IF($B13="","",VLOOKUP($B13,订单!$B$2:$J$29589,MATCH(J$6,订单!$B$1:$I$1,0),FALSE)),"")
B14: =IF(ROW(A8)>MAX(订单!$B:$B),"",ROW(A8)) | C14: =ROW()-6 | D14: =IFERROR(IF($B14="","",VLOOKUP($B14,订单!$B$2:$J$29583,3,FALSE)),"") | F14: =IFERROR(IF($B14="","",VLOOKUP($B14,订单!$B$2:$J$29589,MATCH(F$6,订单!$B$1:$I$1,0),FALSE)),"") | G14: =IFERROR(IF($B14="","",VLOOKUP($B14,订单!$B$2:$J$29589,MATCH(G$6,订单!$B$1:$I$1,0),FALSE)),"") | H14: =IFERROR(IF($B14="","",VLOOKUP($B14,订单!$B$2:$J$29589,MATCH(H$6,订单!$B$1:$I$1,0),FALSE)),"") | I14: =IFERROR(IF($B14="","",VLOOKUP($B14,订单!$B$2:$J$29589,MATCH(I$6,订单!$B$1:$I$1,0),FALSE)),"") | J14: =IFERROR(IF($B14="","",VLOOKUP($B14,订单!$B$2:$J$29589,MATCH(J$6,订单!$B$1:$I$1,0),FALSE)),"")
B15: =IF(ROW(A9)>MAX(订单!$B:$B),"",ROW(A9)) | C15: =ROW()-6 | D15: =IFERROR(IF($B15="","",VLOOKUP($B15,订单!$B$2:$J$29583,3,FALSE)),"") | F15: =IFERROR(IF($B15="","",VLOOKUP($B15,订单!$B$2:$J$29589,MATCH(F$6,订单!$B$1:$I$1,0),FALSE)),"") | G15: =IFERROR(IF($B15="","",VLOOKUP($B15,订单!$B$2:$J$29589,MATCH(G$6,订单!$B$1:$I$1,0),FALSE)),"") | H15: =IFERROR(IF($B15="","",VLOOKUP($B15,订单!$B$2:$J$29589,MATCH(H$6,订单!$B$1:$I$1,0),FALSE)),"") | I15: =IFERROR(IF($B15="","",VLOOKUP($B15,订单!$B$2:$J$29589,MATCH(I$6,订单!$B$1:$I$1,0),FALSE)),"") | J15: =IFERROR(IF($B15="","",VLOOKUP($B15,订单!$B$2:$J$29589,MATCH(J$6,订单!$B$1:$I$1,0),FALSE)),"")
B16: =IF(ROW(A10)>MAX(订单!$B:$B),"",ROW(A10)) | C16: =ROW()-6 | D16: =IFERROR(IF($B16="","",VLOOKUP($B16,订单!$B$2:$J$29583,3,FALSE)),"") | F16: =IFERROR(IF($B16="","",VLOOKUP($B16,订单!$B$2:$J$29589,MATCH(F$6,订单!$B$1:$I$1,0),FALSE)),"") | G16: =IFERROR(IF($B16="","",VLOOKUP($B16,订单!$B$2:$J$29589,MATCH(G$6,订单!$B$1:$I$1,0),FALSE)),"") | H16: =IFERROR(IF($B16="","",VLOOKUP($B16,订单!$B$2:$J$29589,MATCH(H$6,订单!$B$1:$I$1,0),FALSE)),"") | I16: =IFERROR(IF($B16="","",VLOOKUP($B16,订单!$B$2:$J$29589,MATCH(I$6,订单!$B$1:$I$1,0),FALSE)),"") | J16: =IFERROR(IF($B16="","",VLOOKUP($B16,订单!$B$2:$J$29589,MATCH(J$6,订单!$B$1:$I$1,0),FALSE)),"")
B17: =IF(ROW(A11)>MAX(订单!$B:$B),"",ROW(A11)) | C17: =ROW()-6 | D17: =IFERROR(IF($B17="","",VLOOKUP($B17,订单!$B$2:$J$29583,3,FALSE)),"") | F17: =IFERROR(IF($B17="","",VLOOKUP($B17,订单!$B$2:$J$29589,MATCH(F$6,订单!$B$1:$I$1,0),FALSE)),"") | G17: =IFERROR(IF($B17="","",VLOOKUP($B17,订单!$B$2:$J$29589,MATCH(G$6,订单!$B$1:$I$1,0),FALSE)),"") | H17: =IFERROR(IF($B17="","",VLOOKUP($B17,订单!$B$2:$J$29589,MATCH(H$6,订单!$B$1:$I$1,0),FALSE)),"") | I17: =IFERROR(IF($B17="","",VLOOKUP($B17,订单!$B$2:$J$29589,MATCH(I$6,订单!$B$1:$I$1,0),FALSE)),"") | J17: =IFERROR(IF($B17="","",VLOOKUP($B17,订单!$B$2:$J$29589,MATCH(J$6,订单!$B$1:$I$1,0),FALSE)),"")
B18: =IF(ROW(A12)>MAX(订单!$B:$B),"",ROW(A12)) | C18: =ROW()-6 | D18: =IFERROR(IF($B18="","",VLOOKUP($B18,订单!$B$2:$J$29583,3,FALSE)),"") | F18: =IFERROR(IF($B18="","",VLOOKUP($B18,订单!$B$2:$J$29589,MATCH(F$6,订单!$B$1:$I$1,0),FALSE)),"") | G18: =IFERROR(IF($B18="","",VLOOKUP($B18,订单!$B$2:$J$29589,MATCH(G$6,订单!$B$1:$I$1,0),FALSE)),"") | H18: =IFERROR(IF($B18="","",VLOOKUP($B18,订单!$B$2:$J$29589,MATCH(H$6,订单!$B$1:$I$1,0),FALSE)),"") | I18: =IFERROR(IF($B18="","",VLOOKUP($B18,订单!$B$2:$J$29589,MATCH(I$6,订单!$B$1:$I$1,0),FALSE)),"") | J18: =IFERROR(IF($B18="","",VLOOKUP($B18,订单!$B$2:$J$29589,MATCH(J$6,订单!$B$1:$I$1,0),FALSE)),"")
B19: =IF(ROW(A13)>MAX(订单!$B:$B),"",ROW(A13)) | C19: =ROW()-6 | D19: =IFERROR(IF($B19="","",VLOOKUP($B19,订单!$B$2:$J$29583,3,FALSE)),"") | F19: =IFERROR(IF($B19="","",VLOOKUP($B19,订单!$B$2:$J$29589,MATCH(F$6,订单!$B$1:$I$1,0),FALSE)),"") | G19: =IFERROR(IF($B19="","",VLOOKUP($B19,订单!$B$2:$J$29589,MATCH(G$6,订单!$B$1:$I$1,0),FALSE)),"") | H19: =IFERROR(IF($B19="","",VLOOKUP($B19,订单!$B$2:$J$29589,MATCH(H$6,订单!$B$1:$I$1,0),FALSE)),"") | I19: =IFERROR(IF($B19="","",VLOOKUP($B19,订单!$B$2:$J$29589,MATCH(I$6,订单!$B$1:$I$1,0),FALSE)),"") | J19: =IFERROR(IF($B19="","",VLOOKUP($B19,订单!$B$2:$J$29589,MATCH(J$6,订单!$B$1:$I$1,0),FALSE)),"")
... B206: =IF(ROW(A200)>MAX(订单!$B:$B),"",ROW(A200)) | C206: =ROW()-6 | D206: =IFERROR(IF($B206="","",VLOOKUP($B206,订单!$B$2:$J$29583,3,FALSE)),"") | F206: =IFERROR(IF($B206="","",VLOOKUP($B206,订单!$B$2:$J$29589,MATCH(F$6,订单!$B$1:$I$1,0),FALSE)),"") | G206: =IFERROR(IF($B206="","",VLOOKUP($B206,订单!$B$2:$J$29589,MATCH(G$6,订单!$B$1:$I$1,0),FALSE)),"") | H206: =IFERROR(IF($B206="","",VLOOKUP($B206,订单!$B$2:$J$29589,MATCH(H$6,订单!$B$1:$I$1,0),FALSE)),"") | I206: =IFERROR(IF($B206="","",VLOOKUP($B206,订单!$B$2:$J$29589,MATCH(I$6,订单!$B$1:$I$1,0),FALSE)),"") | J206: =IFERROR(IF($B206="","",VLOOKUP($B206,订单!$B$2:$J$29589,MATCH(J$6,订单!$B$1:$I$1,0),FALSE)),"")
C207: 合计 | G207: =SUM(G7:G206) | I207: =SUM(I7:I206)
C208: 总合计（大写） | E208: =IF(I207="","",(IF(I207=0,"零元",TEXT(LEFT(DOLLAR(I207),LEN(DOLLAR(I207))-3),"[>0][dbnum2]G/通用格式元;;;")&TEXT(RIGHT(DOLLAR(I207),2),"[dbnum2]0角0分;;整")))) | H208: （小写）： | I208: =I207
C209: 2、交货期：合同生效后且收到订单全额货款后2-7日内发货（特殊情况协商解决）。
C210: 3、运输方式及地点：物流运输或其他运输方式，地点：需方在本订单中指定的收货地点。
C211: 收货地址：/
C212: 4、运输方式及费用负担：物流或其他货运方式。运费由需方承担。在需方收货并理货后，若因运输导致产品损毁发生纠纷的，由承运方解决，供方协助解决。
C213: 5、发票：商品完成退货周期后的10个工作日，双方确认订单货款已经结清的情况下，供方需将对应的增值税专用发票或者增值税普通发票开具给需求方。
C214: 6、包装标准：按符合产品特性或要求的标准执行
C215: 7、验收标准：按照商品质量管理条例验收，需方应在收货验货后申请退货/换货，需方收货验货无异议视为全部验收合格。若由于产品质量或物流问题导致需方平台无法按时发货，需协商解决。
C216: 8、违约责任：按《中华人民共和国民法典》处理，有关诉讼问题，向供方注册所在地人民法院提起诉讼。
C217: 9、关于售后，属于产品质量问题由供方处理。
C218: 10、本订单一式贰份，供方、需方各执壹份，双方签字（盖章）后生效。
C220: 需方： | F220: 供方：
C221: 单位名称： | E221: =E2 | F221: 单位名称： | G221: 广州启航化妆品科技有限公司
C222: 单位地址： | E222: =IFERROR(VLOOKUP($E$221,开票信息!$C:$I,2,0),"") | F222: 单位地址： | G222: 广州市天河区花城大道20号1301房之五
C223: 代表签字： | F223: 代表签字：
C224: 电 话： | E224: =IFERROR(VLOOKUP($E$221,开票信息!$C:$I,4,0),"") | F224: 电 话： | G224: 020-85676088
C225: 开户银行： | E225: =IFERROR(VLOOKUP($E$221,开票信息!$C:$I,5,0),"") | F225: 开户银行： | G225: 广州农业银行五羊新城支行
C226: 账 号： | E226: =IFERROR(VLOOKUP($E$221,开票信息!$C:$I,6,0),"") | F226: 账 号： | G226: 44031701040024156
C227: 统一社会信用代码： | E227: =IFERROR(VLOOKUP($E$221,开票信息!$C:$I,7,0),"") | F227: 统一社会信用代码： | G227: 91440101MA5CLE6G92

Sheet 开票信息
A1: ﻿合同名称 | B1: 票据类型 | C1: 单位名称 | D1: 单位地址 | E1: 代表签字 | F1: 电 话 | G1: 开户银行 | H1: 账 号 | I1: 统一社会信用代码
A2: 豆妈国际 | B2: 专票 | C2: 上海麟璇国际贸易有限公司 | F2: 17521734768 | G2: 建行上海春申支行 | H2: 31050169550000000262 | I2: 91310112MA1GC99J66
A3: 百合(澜清) | B3: 专票 | C3: 石家庄澜清信息技术有限公司 | D3: 石家庄市长安区平安北大街18号乐模商城南座1416室 | F3: 15227886686 | G3: 中国民生银行股份有限公司石家庄翟营南大街支行 | H3: 602678666 | I3: 91130102094838639T
A4: 甘肃亿呈商贸 | B4: 专票 | C4: 甘肃亿呈商贸有限公司 | D4: 甘肃省兰州市城关区南滨河东路5222号名城广场3号写字楼10楼1011室 | F4: 0931-8431214 | G4: 中国建设银行股份有限公司兰州南昌路支行 | H4: 62050136002600000097 | I4: 91620102 MA73 264B 5Q
A5: 广州珀瑞丝 | B5: 专票 | C5: 广州珀瑞丝化妆品有限公司 | D5: 广州市白云区鹤龙街细彭岭路10号汇龙国际电商产业园C栋607室 | F5: 020-29031126 | G5: 平安银行广州万达广场支行 | H5: 15079171820014 | I5: 91440106MACB55421B
A6: 富德隆 | B6: 专票 | C6: 深圳市富德隆科技有限公司 | D6: 深圳市龙岗区平湖街道平湖社区平湖大道满庭芳花园5栋2单元504 | F6: 13714636790 | G6: 中国建设银行股份有限公司深圳市分行 | H6: 44201501100052545830 | I6: 914403000539900951
A7: 喜辉以禾 | B7: 专票 | C7: 喜辉以禾实业(上海)有限公司 | D7: 上海市嘉定区众仁路399号1幢12层B区JT13943室 | F7: 13622336490 | G7: 中国银行上海市博乐路支行 | H7: 437788596776 | I7: 91310114MAE6627T8U
A8: 上海蕤翔实业有限公司 | B8: 专票 | C8: 上海蕤翔实业有限公司 | D8: 上海市普陀区绥德路555号D栋508 | F8: 17602100116 | G8: 中国银行上海市桃浦支行 | H8: 453385607416 | I8: 91310107MACXJ1KC09
A9: 上海心满 | C9: 上海心满商贸有限公司 | D9: 上海市嘉定区嘉罗公路1661弄12号101室J557 | F9: 021-59558669 | G9: 中国农业银行股份有限公司上海闵行虹桥支行 | H9: 03407500040030659 | I9: 91310114MA1GTURW7R
A10: 宁波晟淘 | B10: 专票
A11: 中盛瑞尔 | B11: 专票
A12: 荃心商贸 | B12: 专票 | C12: 杭州荃心商贸有限公司 | D12: 浙江省杭州市余杭区五常街道邦帮金座2幢 | F12: 57185063196 | G12: 中国农业银行杭州古荡支行 | H12: 19000801040017866 | I12: 91330110MA2B00641X
A13: 清滋 | B13: 专票 | C13: 上海清滋商贸有限公司 | D13: 浦东新区万祥镇宏祥北路83弄1-42号20幢118室 31391827 | F13: 18916357868 | G13: 中国工商银行上海市甘泉新村支行 | H13: 1001042209000004540 | I13: 91310115MA1H8F0W05
A14: 才赋 | B14: 专票 | C14: 上海才赋人力资源科技有限公司 | D14: 上海市普陀区大渡河路556弄1号国浩长风城南座1101室 | F14: 8621-32581281 | G14: 招商银行上海分行虹桥支行 | H14: 1219 2401 8610 702 | I14: 91310107MA1G0DTX3H
A15: 快愉 | B15: 嘉博专票 | C15: 嘉博伟创（江苏）贸易有限公司 | D15: 镇江市京口区中山东路301号苏宁广场塔楼A 单元1305室 | F15: 15651287585 | G15: 农行镇江京口支行 | H15: 10311101040241705 | I15: 91321102MA27M93K4L
A16: 快愉 | B16: 快愉专票 | C16: 快愉（上海）电子商务有限公司 | D16: 上海市宝山区潘泾路5777弄188号3层3274室 | F16: 15651287585 | G16: 中国农业银行股份有限公司上海真北路支行 | H16: 03477400040014738 | I16: 91310120067750631Q
A17: 和润晟(专票) | C17: 山西和润晟贸易有限公司 | D17: 山西省太原市万柏林区迎泽西大街100号国际能源中心26层2605-1室 | F17: 18334789091 | G17: 中国工商银行股份有限公司太原迎泽支行 | H17: 0502207009200052158 | I17: 91140100MA0M0PGC56
A18: 九美子 | B18: 长沙赛尔专票 | C18: 长沙赛尔贸易有限公司 | D18: 长沙市雨花区南二环一段路55号叠彩峰苑B区2栋1802房 | G18: 中信银行长沙人民路支行 | H18: 8111 6010 11700 581910 | I18: 91430111MA4R7DQ16A
A19: 九美子 | B19: 上海冰雾专票 | C19: 上海冰雾网络科技有限公司 | D19: 上海市闵行区联川路319号3幢205室 | F19: 021-60960807 | G19: 中国民生银行股份有限公司上海南汇支行 | H19: 159660157 | I19: 91310112MA1GCHQX0X
A20: 上海敏君 | B20: 专票 | C20: 上海敏君实业有限公司 | D20: 上海市青浦区徐泾镇双联路388号2号楼7楼 | F20: 021-31781587 | G20: 浙江泰隆银行上海嘉定支行 | H20: 3101050120100015551 | I20: 91310113062571220C
A21: 鑫万齐 | B21: 专票 | C21: 鑫万齐（天津）科技有限公司 | D21: 天津经济技术开发区滨海-中关村科技园融汇商务5区1号楼二层-78号 | F21: 18201140387 | G21: 招商银行股份有限公司天津南京路支行（回款账户首选） | H21: 122917517910001 | I21: 91120116MACPUGA53J
A22: 颐佰(专票)剩下的金金开
A23: 全晟商贸 | B23: 专票 | C23: 山东全晟商贸有限公司 | D23: 山东省日照市经济开发区北京路277号航贸中心A座2101 | G23: 中国农业银行股份有限公司日照市分行 | H23: 15651001040052755 | I23: 91371103MA954NM10F
A24: 先迈网 | B24: 专票 | C24: 大连好麦檬信息科技有限公司 | D24: 辽宁省大连经济技术开发区城润万家78栋-4号 | F24: 18804202893 | G24: 中国民生银行股份有限公司大连金州支行 | H24: 644575079 | I24: 91210213MADA1E5F89
A25: 武汉利尔亿 | B25: 专票 | C25: 武汉利尔亿商贸有限公司 | D25: 武汉市硚口区解放正巷68号 | F25: 027-85676702 | G25: 中国工商银行武汉市汉正街支行 | H25: 3202013509200210117 | I25: 91420104MA4K3EWHX9
A26: bmclub | B26: 专票 | C26: 南京安田羽铭商贸有限公司 | D26: 南京市鼓楼区江东北路88号2412室 | F26: 18651825755 | G26: 中国银行股份有限公司南京云锦路支行 | H26: 546975827242 | I26: 91320106MA256HNQ3G
A27: 柠檬阿姨美妆 | B27: 杭州柠芒椒创普票 | C27: 杭州柠芒椒创电子商务有限公司 | G27: 杭州银行 | H27: 3301 0410 6000 7331444 | I27: 91330113MAK5XF084B
A28: 欧妮 | B28: 家亨专票剩下的金子开 | D28: 安徽省合肥市长丰县双墩镇滁河社区规划支路S2栋B85室 | F28: 17857443206 | G28: 中国工商银行股份有限公司长丰双凤支行 | H28: 1302052309100167043 | I28: 91330282MAC7LUQM78
A29: 欧妮 | B29: 亨浩专票剩下的金子开
A30: 达达妈 | B30: 专票 | C30: 合肥磐韦电子商务有限公司 | D30: 安徽省合肥市长丰县双墩镇濛河路1号创孵中心E821 | F30: 15161459392 | G30: 招商银行股份有限公司合肥瑶海支行 | H30: 551907288510902 | I30: 91340121MA8N1J6P22
A31: 柠月美妆 | B31: 普票剩下的金子开 | C31: 义乌市比先化妆品有限公司 | D31: 浙江省金华市义乌市廿三里街道草湖塘小区3栋一单元307室（自主申报） | F31: 15805799494 | G31: 中国工商银行股份有限公司义乌商城支行营业部 | H31: 1208021409100112956 | I31: 91330782MA2K0KP10E
A32: 知品美妆 | B32: 专票 | C32: 深圳市佰祺电子商务有限公司 | D32: 深圳市龙岗区坂田街道马安堂社区环城南路15号恒大都会广场1栋1910-2 | F32: 13005498285 | G32: 广发银行股份有限公司深圳坂田支行 | H32: 9550880231159200141 | I32: 91440300MA5H3KQY6N
A33: 上海宇致 | B33: 专票 | C33: 上海宇致实业有限公司 | D33: 上海市闵行区联川路319号2幢403室 | F33: 021-60960807 | G33: 浙江泰隆商业银行上海周浦支行 | H33: 31010220201000044560 | I33: 91310113312209903Y
A34: 中节能 | B34: 专票 | C34: 中节能环保投资发展（江西）有限公司工会委员会 | D34: 江西省南昌市高新区中节能国际中心1号楼 | I34: 81360000MCA133032F
A35: 雪玲妃专柜正品特价店 | B35: 个人票 | C35: 上海麟璇国际贸易有限公司 | F35: 17521734768 | G35: 建行上海春申支行 | H35: 31050169550000000262 | I35: 91310112MA1GC99J66
A36: zz思密达杂货铺 | B36: 个人票 | C36: 上海麟璇国际贸易有限公司 | F36: 17521734768 | G36: 建行上海春申支行 | H36: 31050169550000000262 | I36: 91310112MA1GC99J66
A37: 大宋宋美妆 | B37: 普票 | C37: 上海黑黛黛品牌管理有限公司 | D37: 上海市金山区亭林镇天工路285弄38号（恒信源经济园区） | F37: 13391126136 | G37: 招商银行股份有限公司上海准中支行 | H37: 121950974010701 | I37: 91310116MACDC1ET54
A38: 一只毛吉吉 | B38: 普票 | C38: 桂林市临桂区有个朋友网络销售经营部 | D38: 临桂区临桂镇桂康鸿湖园D11栋2号 | F38: 18907731385 | G38: 招商银行股份有限公司上海北外滩支行 | H38: 121954641710001 | I38: 92450312MADKKQNM53
A39: 广盈和创 | B39: 专票 | C39: 深圳市广盈和创贸易有限公司 | D39: 深圳市福田区莲花街道福中社区金田路4028号荣超经贸中心A309-AJ84 | F39: 14714932220 | G39: 中国银行深圳北方大厦支行 | H39: 747179152120 | I39: 91440300MAE12U807G
A40: 广盈特联 | B40: 专票 | C40: 广盈特联(深圳)供应链有限公司 | D40: 深圳市福田区华强北街道福强社区振华路中电迪富大厦4层411室 | F40: 13043489506 | G40: 中国农业银行深圳塘朗支行 | H40: 41009800040000873 | I40: 91440300MA5GCXQR2G
A41: 黑胡椒 | B41: 个人支付宝打款
A42: 德国小佛爷 | B42: 个人票 | C42: 谈静仪
A43: 阿拉蕾(专票) | C43: 杭州阿啦蕾供应链管理有限公司 | D43: 浙江省杭州市萧山区宁围街道耕文路78号浙大科技园萧龙科创中心3幢716-13室 | F43: 13858100184 | G43: 中国农业银行股份有限公司杭州九堡支行 | H43: 19033301040024369 | I43: 91330104MA28XXX327
A44: 阿拉蕾(专票) (弘乐) | C44: 杭州阿啦蕾供应链管理有限公司 | D44: 浙江省杭州市萧山区宁围街道耕文路78号浙大科技园萧龙科创中心3幢716-13室 | F44: 13858100184 | G44: 中国农业银行股份有限公司杭州九堡支行 | H44: 19033301040024369 | I44: 91330104MA28XXX327
A45: 小奶牛(明溪欧顺佳专票) | C45: 明溪欧顺佳品牌运营管理有限公司 | D45: 福建省明溪县胡坊镇胡东街28号 | F45: 13960766560 | G45: 中国建设银行股份有限公司明溪支行 | H45: 35050164720700001045 | I45: 91350421MAEBGTYF8Y
A46: 小奶牛(明溪县熙澜映专票) | C46: 明溪县熙澜映贸易有限公司 | D46: 福建省明溪县胡坊镇奋发村1-4号 | F46: 13960533368 | G46: 中国建设银行股份有限公司明溪支行 | H46: 35050164720700001118 | I46: 91350421MAER8UFT59
A47: 小娴 | B47: 菲奥娜普票 | G47: 招商银行股份有限公司杭州分行营业部 | H47: 571918091510201 | I47: 91330109MABT04CK4N
A48: 小娴 | B48: 厦门金峤专票 | C48: 厦门金峤品牌管理有限公司 | D48: 厦门市集美区内东路121号101室 | F48: 13414113453 | G48: 中国民生银行股份有限公司厦门软件园支行 | H48: 645786310 | I48: 91350211MADHJT4391
A49: 薇安萧 | B49: 珈倍美丽专票 | C49: 深圳市珈倍美丽电子商务有限公司 | D49: 广东省深圳市宝安区海天路15号 前海卓越时代广场A座1806A房 | F49: 13798505060 | G49: 中国平安银行深圳宝城支行 | H49: 15000415870055 | I49: 91440300MAK3891K4K
A50: 么么小玄子 | B50: 专票 | C50: 青岛尚云化妆品有限公司 | D50: 山东省青岛市城阳区城阳街道正阳中路166号天一仁和财富中心6号楼办公5层527 | F50: 15066689210 | G50: 平安银行青岛分行营业部 | H50: 15771224060065 | I50: 91370214MADX7DAU3Q
A51: 中屹 | B51: 盈耶针织普票
A52: 中屹 | B52: 玲溪针织普票
A53: 中屹 | B53: 褚壹普票
A54: 中屹 | B54: 中屹普票
A55: 中屹 | B55: 一箱盒情愿普票
A56: 中屹 | B56: 山东沂库普票弘乐
A57: 中屹 | B57: 山东沂库普票
A58: 中屹 | B58: 山东大仓普票
A59: 米乐个护专营店 | B59: 普票
A60: 小妲己试色小样(臻泰专票) | C60: 深圳市臻泰供应链有限公司 | G60: 平安银行深圳分行营业部 | H60: 1500 3033 6327 76 | I60: 91440300MAEQ2XMK02
A61: 小妲己试色小样(长泰专票) | C61: 深圳市长泰供应链有限公司 | D61: 深圳市南山区西丽街道松坪山社区乌石头路8号天明科技大厦6D34 | F61: 15018387557 | G61: 中国建设银行股份有限公司深圳景苑支行 | H61: 44250100008600005614 | I61: 91440300MAK7DE0X9W
A62: 小妲己试色小样(晶妆专票) | C62: 重庆晶妆国际贸易有限公司 | D62: 重庆市沙坪坝区联芳桥13号2号楼2-社区用房1自编号：1-40 | F62: 13456203556 | G62: 中国农业银行股份有限公司重庆渝中大坪支行 | H62: 31-020801040022201 | I62: 91500106MAELL6F916
A63: 野孩子的美妆店(专票) | C63: 台州酷孩电子商务有限公司 | D63: 浙江省台州市椒江区洪家街道银泰路89号心海数贸港D幢2楼2F001-7 | F63: 13157637777 | G63: 上海浦东发展银行台州椒江支行 | H63: 81040078801200001064 | I63: 91331002MAE9R2YMX8
A64: 钱包黑洞 | B64: 专票 | D64: 福建省厦门市集美区杏林湾路478号802室之二 | G64: 中国工商银行厦门杏林支 | H64: 4100022109200314706 | I64: 91350211MAE04PAD20
A65: 拾掇妈 | B65: 安徽方荀专票 | C65: 安徽方荀电子商务有限公司 | D65: 安徽省合肥市长丰县双凤经济开发区梅冲湖路双凤智谷创创业科技园A栋907-002室 | F65: 18963511212 | G65: 兴业银行股份有限公司合肥分行 | H65: 499010100102201331 | I65: 91340221MA8QPQJT03
A66: 拾掇妈 | B66: 芜湖鸣蝉专票 | C66: 芜湖鸣蝉电子商务有限公司 | D66: 安徽省芜湖市湾沚区红杨镇原新桥村村部大楼2-101号 | F66: 18963511212 | G66: 兴业银行股份有限公司合肥分行 | H66: 499010100102338581 | I66: 91340221MADRKB3K71
A67: 飞奔的温暖 | B67: 觅余悠可专票 | C67: 青岛觅余悠可商贸有限公司 | D67: 山东省青岛市城阳区锦城路357号8号楼办公701户 | F67: 18561760562 | G67: 青岛银行股份有限公司城阳支行 | H67: 802210201157505 | I67: 91370214MA954QC4XE
A68: 飞奔的温暖 | B68: 姝姝百库专票皮皮的破店一起开 | C68: 青岛姝姝百库电子商贸有限公司 | D68: 山东省青岛市李沧区巨峰路176号信联天地2号楼5层504-8室 | F68: 13357007908 | G68: 中国建设银行股份有限公司青岛李沧支行 | H68: 37150198651000005338 | I68: 91370213MADPXGYQ6J
A69: 飞奔的温暖 | B69: 十宜佳宁专票 | C69: 青岛十宜佳宁电子商贸有限公司 | D69: 山东省青岛市城阳区流亭街道南流路9号盛豪5G数字智能物流产业园1号楼115室 | F69: 13127026103 | G69: 中国工商银行股份有限公司青岛流亭支行 | H69: 3803255209000126426 | I69: 91370214MADPR8MA4G
A70: 飞奔的温暖 | B70: 朱脸脸专票皮皮的破店一起开 | C70: 青岛朱脸脸化妆品商贸有限公司 | D70: 山东省青岛市李沧区巨峰路176号信联天地2号楼5层504-7室 | F70: 13837117194 | G70: 中信银行股份有限公司青岛李沧支行 | H70: 8110601012801768894 | I70: 91370213MADPJYXT72
A71: 皮皮的一个破店 | B71: 青岛鱼己己专票 | C71: 青岛鱼己己商贸合伙企业(有限合伙) | D71: 山东省青岛胶州市三里河街道香港路478号上合国际人才双创产业园A栋608室 | F71: 13606348592 | G71: 中国工商银行股份有限公司胶州扬州路支行 | H71: 3803058209100044924 | I71: 91370281MAEQNH5J5L
A72: 皮皮 kiko | B72: 青岛鱼己己专票 | C72: 青岛鱼己己商贸合伙企业(有限合伙) | D72: 山东省青岛胶州市三里河街道香港路478号上合国际人才双创产业园A栋608室 | F72: 13606348592 | G72: 中国工商银行股份有限公司胶州扬州路支行 | H72: 3803058209100044924 | I72: 91370281MAEQNH5J5L
A73: 小王子 | B73: 金华市俏娜专票 | C73: 金华市俏娜化妆品有限公司 | D73: 浙江省义乌市江东街道青口东苑路62号3号楼7楼703室 | F73: 13357007908 | G73: 中国建设银行股份有限公司义乌分行 | H73: 33050167623500001642 | I73: 91330782MA28EH932Q
A74: 小王子 | B74: 金华市叮呤专票 | C74: 金华市叮呤电子商务有限公司 | D74: 浙江省义乌市江东街道青口东苑路62号3号楼7楼703室 | F74: 13357007908 | G74: 中国工商银行股份有限公司义乌分行 | H74: 1208020009200357003 | I74: 91330782MA28EH932Q
A75: 小王子 | B75: 专票 | C75: 金华市俏娜化妆品有限公司 | D75: 浙江省义乌市江东街道青口东苑路62号3号楼7楼703室 | F75: 13357007908 | G75: 中国建设银行股份有限公司义乌分行 | H75: 33050167623500001642 | I75: 91330782MA28EH932Q
A76: 宝贝可爱 | B76: 安徽网尊专票 | D76: 合肥市高新区天波路19号天怡国际商务中心401室 | F76: 18616605422 | G76: 招商银行股份有限公司合肥高新区支行 | H76: 551905536710901 | I76: 91340100MA2NWKW20Q
A77: 宝贝可爱 | B77: 合肥买买乐专票 | D77: 合肥市高新区天波路19号天怡国际商务中心401室 | F77: 18616605422 | G77: 招商银行股份有限公司合肥科大硅谷支行 | H77: 551911126210000 | I77: 91340100MAKD9Q1X1H
A78: 白富美 | B78: 奉炜专票 | C78: 上海奉炜网络科技有限公司 | D78: 上海市奉贤区望园路1698弄2号7幢105室 | F78: 021-52273108 | G78: 招商银行上海分行上海闵行支行 | H78: 121930422410902 | I78: 91310116MA1J981N1X
A79: 白富美 | B79: 宜兴专票 | C79: 宜兴妍护健康科技有限公司 | D79: 宜兴市宜城街道解放东路299号 | F79: 13248000510 | G79: 招商银行股份有限公司宜兴支行 | H79: 610902968610000 | I79: 91320282MADLD2KJ9P
A80: 白富美 | B80: 奉炜专票以往代发单 | C80: 上海奉炜网络科技有限公司 | D80: 上海市奉贤区望园路1698弄2号7幢105室 | F80: 021-52273108 | G80: 招商银行上海分行上海闵行支行 | H80: 121930422410902 | I80: 91310116MA1J981N1X
A81: 白富美 | B81: 要妆专票 | C81: 要妆科技（上海）有限公司 | D81: 上海市奉贤区望园路1698弄2号7幢206室 | F81: 021-52273108 | G81: 招商银行股份有限公司上海奉贤支行 | H81: 121945955510801 | I81: 91310120MA1HREJ782
A82: 白富美 | B82: 奉芈专票 | C82: 上海奉芈网络科技有限公司 | D82: 上海市奉贤区望园路1698弄2号7幢105室 | F82: 021-52273108 | G82: 招商银行上海分行上海闵行支行 | H82: 6.23262e+15 | I82: 91310116MA1J981N1X
A83: 凝哥 | B83: 行予专票 | C83: 宁波行予化妆品销售有限公司 | D83: 浙江省宁波市镇海区骆驼街道汇水路128 号3号 302 | F83: 13616575086 | G83: 招商银行股份有限公司合肥滨湖支行 | H83: 551908561110001 | I83: 91340104MAD720DG1R
A84: 凝哥 | B84: 晚予专票 | C84: 四川省晚予化妆品销售有限公司 | D84: 四川省宜宾市兴文县古宋镇温水溪村和润城南首府12号楼4层 | F84: 17306505620 | G84: 招商银行宁波分行宁波镇海支行 | H84: 574910884710001 | I84: 91511528MAEBCA5903
A85: 凝哥 kiko | B85: 晚予专票 | C85: 四川省晚予化妆品销售有限公司 | D85: 四川省宜宾市兴文县古宋镇温水溪村和润城南首府12号楼4层 | F85: 17306505620 | G85: 招商银行宁波分行宁波镇海支行 | H85: 574910884710001 | I85: 91511528MAEBCA5903
A86: 小异地 | B86: 嘉景专票 | C86: 深圳市嘉景品牌管理有限公司 | D86: 深圳市龙岗区横岗街道松柏社区龙岗大道（横岗段）5008号港信达横岗大厦1710 | F86: 15994832749 | G86: 中国银行股份有限公司深圳莲塘支行 | H86: 754976397933 | I86: 91440300MA5HK67P6W
A87: 小异地 | B87: 希贤专票 | C87: 深圳市希贤品牌管理有限公司 | D87: 深圳市龙岗区横岗街道松柏社区龙岗大道（横岗段）5008号港信达横岗大厦1711 | F87: 13787811787 | G87: 深圳福田银座村镇银行股份有限公司 | H87: 651231366100015 | I87: 91440300MADNY7L34N
A88: 小异地 kiko | B88: 希贤专票 | C88: 深圳市希贤品牌管理有限公司 | D88: 深圳市龙岗区横岗街道松柏社区龙岗大道（横岗段）5008号港信达横岗大厦1711 | F88: 13787811787 | G88: 深圳福田银座村镇银行股份有限公司 | H88: 651231366100015 | I88: 91440300MADNY7L34N
A89: 小异地bblab | B89: 嘉景专票 | C89: 深圳市嘉景品牌管理有限公司 | D89: 深圳市福田区园岭街道鹏盛社区八卦一路八卦岭工业区619栋430A | F89: 15994832749 | G89: 中国银行股份有限公司深圳莲塘支行 | H89: 754976397933 | I89: 91440300MA5HK67P6W
A90: 小异地bblab | B90: 希贤专票 | C90: 深圳市希贤品牌管理有限公司 | D90: 深圳市龙岗区横岗街道松柏社区龙岗大道（横岗段）5008号港信达横岗大厦1711 | F90: 137 8781 1787 | G90: 深圳福田银座村镇银行股份有限公司 | H90: 651231366100015 | I90: 91440300MADNY7L34N
A91: 脸妹 kiko | B91: 脸掌柜专票 | C91: 脸掌柜（深圳）网络科技有限公司 | D91: 广东省深圳市龙岗区龙城街道爱联社区中粮祥云广场2A栋1309室 | F91: 17722411118 | G91: 招商银行深圳横岗支行 | H91: 755961641810901 | I91: 91440300MA5HFA0L2K
A92: 脸妹 | B92: 脸掌柜专票 | C92: 脸掌柜（深圳）网络科技有限公司 | D92: 广东省深圳市龙岗区龙城街道爱联社区中粮祥云广场2A栋1309室 | F92: 17722411118 | G92: 招商银行深圳横岗支行 | H92: 755961641810901 | I92: 91440300MA5HFA0L2K
A93: 脸妹 | B93: 蒂缇专票 | C93: 蒂缇(深圳)电子商务有限公司 | D93: 广东省深圳市龙岗区龙城街道爱联社区中粮祥云广场2A栋1308室 | F93: 13863762270 | G93: 招商银行深圳横岗支行 | H93: 755941956410301 | I93: 91440300MA5FERRCXC
A94: 你好宝贝 | B94: 扶摇而上专票 | C94: 杭州扶摇而上电子商务有限公司 | D94: 浙江省杭州市萧山区所前镇东藩路62号笨鸟邦科技创业园1288号 | F94: 15810515028 | G94: 中国工商银行杭州三里亭支行 | H94: 1202027509100034001 | I94: 91330109MABM6C5N27
A95: 苏小凡 | B95: 金大条专票 | C95: 厦门市思明区金大条日用品店(个体工商户) | G95: 中国建设银行股份有限公司厦门科技支行 | H95: 35150198870100003663 | I95: 92350203MADT32QL6T
A96: 苏小凡 | B96: 金大花普票 | C96: 厦门市湖里区金大花日用品店(个体工商户) | G96: 兴业银行厦门湖里支行 | H96: 129920100100721238 | I96: 92350206MAENH8D51C
A97: 四月七 | B97: 棱点专票 | D97: 厦门市思明区金桥路20号1305室之三 | F97: 13395003789 | G97: 厦门建设银行康乐银行 | H97: 35150198350100000835 | I97: 91350206MA8W23050L
A98: 四月七 | B98: 禾二专票 | D98: 厦门市集美区塘埔路71号601室 | G98: 中国建设银行股份有限公司厦门康乐支行 | H98: 35150198350100000778 | I98: 91440800560877978X
A99: 四月七 | B99: 叶贝专票 | D99: 厦门市湖里区湖里大道2-15号205室之十七 | F99: 13599925662 | G99: 中国建设银行股份有限公司厦门康乐支行 | H99: 35150198350100000073 | I99: 91350206MA346LW93X
A100: 四月七 | B100: 棱启专票 | D100: 中国(福建)自由贸易试验区厦门片区殿前六路509号210室 | F100: 13860171240 | G100: 中国工商银行股份有限公司厦门康乐支行 | H100: 4100024709200108041 | I100: 91350206MA8TWTR46E
...

Sheet 订单
A1: 序号 | B1: 序号 | C1: 需求方（甲方） | D1: 产品名称 | E1: 单位 | F1: 数量 | G1: 单价（人民币） | H1: 金额（元） | I1: 备注 | J1: 销售 | K1: 需求方（甲方）
A2: 1 | B2: =COUNTIF($C$2:$C2,模板!$E$2) | C2: 677design | D2: Lycocelle绽家内衣洗衣液100ml（经典） | F2: 1 | G2: =IFERROR(H2/F2,"") | H2: 0 | J2: 咏琪 | K2: 677design | L2: =COUNTIF($K2:K$2,$K2)
A3: 2 | B3: =COUNTIF($C$2:$C3,模板!$E$2) | C3: 677design | D3: Lycocelle绽家内衣洗衣液330ml（经典） | F3: 1 | G3: =IFERROR(H3/F3,"") | H3: 24 | J3: 咏琪 | K3: 677design | L3: =COUNTIF($K$2:K3,$K3)
A4: 3 | B4: =COUNTIF($C$2:$C4,模板!$E$2) | C4: BBS小鲨鱼 | D4: Lycocelle绽家内衣洗衣液100ml（经典） | F4: 10 | G4: =IFERROR(H4/F4,"") | H4: 0 | J4: 彭珠 | K4: BBS小鲨鱼 | L4: =COUNTIF($K$2:K4,$K4)
A5: 4 | B5: =COUNTIF($C$2:$C5,模板!$E$2) | C5: BBS小鲨鱼 | D5: Lycocelle绽家内衣洗衣液330ml（七月炉火） | F5: 3 | G5: =IFERROR(H5/F5,"") | H5: 73.5 | J5: 彭珠 | K5: BBS小鲨鱼 | L5: =COUNTIF($K$2:K5,$K5)
A6: 5 | B6: =COUNTIF($C$2:$C6,模板!$E$2) | C6: BBS小鲨鱼 | D6: Lycocelle绽家内衣洗衣液330ml（爱丽斯梦境） | F6: 2 | G6: =IFERROR(H6/F6,"") | H6: 49 | J6: 彭珠 | K6: BBS小鲨鱼 | L6: =COUNTIF($K$2:K6,$K6)
A7: 6 | B7: =COUNTIF($C$2:$C7,模板!$E$2) | C7: BBS小鲨鱼 | D7: Lycocelle绽家内衣洗衣液330ml（玫瑰与蔷薇） | F7: 6 | G7: =IFERROR(H7/F7,"") | H7: 147 | J7: 彭珠 | K7: BBS小鲨鱼 | L7: =COUNTIF($K$2:K7,$K7)
A8: 7 | B8: =COUNTIF($C$2:$C8,模板!$E$2) | C8: BBS小鲨鱼 | D8: Lycocelle绽家内衣洗衣液330ml（粉红葡萄柚） | F8: 4 | G8: =IFERROR(H8/F8,"") | H8: 98 | J8: 彭珠 | K8: BBS小鲨鱼 | L8: =COUNTIF($K$2:K8,$K8)
A9: 8 | B9: =COUNTIF($C$2:$C9,模板!$E$2) | C9: BBS小鲨鱼 | D9: Lycocelle绽家内衣洗衣液330ml（经典） | F9: 5 | G9: =IFERROR(H9/F9,"") | H9: 122.5 | J9: 彭珠 | K9: BBS小鲨鱼 | L9: =COUNTIF($K$2:K9,$K9)
A10: 9 | B10: =COUNTIF($C$2:$C10,模板!$E$2) | C10: BBS小鲨鱼 | D10: Lycocelle绽家四季繁花酵素香氛洗衣液480ml（无花果与奶檀）-袋装 | F10: 4 | G10: =IFERROR(H10/F10,"") | H10: 0 | J10: 彭珠 | K10: BBS小鲨鱼 | L10: =COUNTIF($K$2:K10,$K10)
A11: 10 | B11: =COUNTIF($C$2:$C11,模板!$E$2) | C11: BBS小鲨鱼 | D11: Lycocelle绽家四季繁花酵素香氛洗衣液480ml（甜橙与百里香）-袋装 | F11: 2 | G11: =IFERROR(H11/F11,"") | H11: 0 | J11: 彭珠 | K11: BBS小鲨鱼 | L11: =COUNTIF($K$2:K11,$K11)
A12: 11 | B12: =COUNTIF($C$2:$C12,模板!$E$2) | C12: BBS小鲨鱼 | D12: Lycocelle绽家四季繁花酵素香氛洗衣液600ml（无花果与奶檀）-方瓶 | F12: 1 | G12: =IFERROR(H12/F12,"") | H12: 35 | J12: 彭珠 | K12: BBS小鲨鱼 | L12: =COUNTIF($K$2:K12,$K12)
A13: 12 | B13: =COUNTIF($C$2:$C13,模板!$E$2) | C13: BBS小鲨鱼 | D13: Lycocelle绽家四季繁花香氛衣物柔顺剂300ml（桂花与清酒) | F13: 3 | G13: =IFERROR(H13/F13,"") | H13: 0 | J13: 彭珠 | K13: BBS小鲨鱼 | L13: =COUNTIF($K$2:K13,$K13)
A14: 13 | B14: =COUNTIF($C$2:$C14,模板!$E$2) | C14: BBS小鲨鱼 | D14: Lycocelle绽家护衣留香珠（一杯鲜橙）180g | F14: 1 | G14: =IFERROR(H14/F14,"") | H14: 0 | J14: 彭珠 | K14: BBS小鲨鱼 | L14: =COUNTIF($K$2:K14,$K14)
... A79: 78 | B79: =COUNTIF($C$2:$C79,模板!$E$2) | C79: BBS小鲨鱼 | D79: 绽家香水油浓缩洗衣液（雨后檀木鸢尾花）800mL-联名版 | F79: 1 | G79: =IFERROR(H79/F79,"") | H79: 51 | J79: 彭珠 | K79: BBS小鲨鱼 | L79: =COUNTIF($K$2:K79,$K79)
A80: 79 | B80: =COUNTIF($C$2:$C80,模板!$E$2) | C80: =IFERROR(VLOOKUP(K80,开票信息!$A:$C,3,0),"") | D80: Lycocelle绽家内衣洗衣液330ml（爱丽斯梦境） | F80: 6 | G80: =IFERROR(H80/F80,"") | H80: 150 | J80: 秋容 | K80: BMCLUB | L80: =COUNTIF($K$2:K80,$K80)
A81: 80 | B81: =COUNTIF($C$2:$C81,模板!$E$2) | C81: =IFERROR(VLOOKUP(K81,开票信息!$A:$C,3,0),"") | D81: Lycocelle绽家内衣洗衣液330ml（玫瑰与蔷薇） | F81: 5 | G81: =IFERROR(H81/F81,"") | H81: 125 | J81: 秋容 | K81: BMCLUB | L81: =COUNTIF($K$2:K81,$K81)
A82: 81 | B82: =COUNTIF($C$2:$C82,模板!$E$2) | C82: =IFERROR(VLOOKUP(K82,开票信息!$A:$C,3,0),"") | D82: Lycocelle绽家内衣洗衣液330ml（粉红葡萄柚） | F82: 5 | G82: =IFERROR(H82/F82,"") | H82: 125 | J82: 秋容 | K82: BMCLUB | L82: =COUNTIF($K$2:K82,$K82)
A83: 82 | B83: =COUNTIF($C$2:$C83,模板!$E$2) | C83: =IFERROR(VLOOKUP(K83,开票信息!$A:$C,3,0),"") | D83: Lycocelle绽家内衣洗衣液330ml（经典） | F83: 8 | G83: =IFERROR(H83/F83,"") | H83: 200 | J83: 秋容 | K83: BMCLUB | L83: =COUNTIF($K$2:K83,$K83)
A84: 83 | B84: =COUNTIF($C$2:$C84,模板!$E$2) | C84: =IFERROR(VLOOKUP(K84,开票信息!$A:$C,3,0),"") | D84: Lycocelle绽家四季繁花酵素香氛洗衣液480ml（无花果与奶檀）-袋装 | F84: 26 | G84: =IFERROR(H84/F84,"") | H84: 260 | J84: 秋容 | K84: BMCLUB | L84: =COUNTIF($K$2:K84,$K84)
A85: 84 | B85: =COUNTIF($C$2:$C85,模板!$E$2) | C85: =IFERROR(VLOOKUP(K85,开票信息!$A:$C,3,0),"") | D85: Lycocelle绽家四季繁花酵素香氛洗衣液480ml（甜橙与百里香）-袋装 | F85: 13 | G85: =IFERROR(H85/F85,"") | H85: 130 | J85: 秋容 | K85: BMCLUB | L85: =COUNTIF($K$2:K85,$K85)
A86: 85 | B86: =COUNTIF($C$2:$C86,模板!$E$2) | C86: =IFERROR(VLOOKUP(K86,开票信息!$A:$C,3,0),"") | D86: Lycocelle绽家四季繁花酵素香氛洗衣液480ml（迈索尔檀木与小花茉莉）-袋装 | F86: 9 | G86: =IFERROR(H86/F86,"") | H86: 90 | J86: 秋容 | K86: BMCLUB | L86: =COUNTIF($K$2:K86,$K86)
A87: 86 | B87: =COUNTIF($C$2:$C87,模板!$E$2) | C87: =IFERROR(VLOOKUP(K87,开票信息!$A:$C,3,0),"") | D87: Lycocelle绽家四季繁花酵素香氛洗衣液600ml（无花果与奶檀）-方瓶 | F87: 2 | G87: =IFERROR(H87/F87,"") | H87: 36 | J87: 秋容 | K87: BMCLUB | L87: =COUNTIF($K$2:K87,$K87)
A88: 87 | B88: =COUNTIF($C$2:$C88,模板!$E$2) | C88: =IFERROR(VLOOKUP(K88,开票信息!$A:$C,3,0),"") | D88: Lycocelle绽家四季繁花酵素香氛洗衣液600ml（杏仁奶檀）-方瓶 | F88: 1 | G88: =IFERROR(H88/F88,"") | H88: 18 | J88: 秋容 | K88: BMCLUB | L88: =COUNTIF($K$2:K88,$K88)
A89: 88 | B89: =COUNTIF($C$2:$C89,模板!$E$2) | C89: =IFERROR(VLOOKUP(K89,开票信息!$A:$C,3,0),"") | D89: Lycocelle绽家四季繁花酵素香氛洗衣液（迈索尔檀木与小花茉莉）30ml | F89: 7 | G89: =IFERROR(H89/F89,"") | H89: 0 | J89: 秋容 | K89: BMCLUB | L89: =COUNTIF($K$2:K89,$K89)
A90: 89 | B90: =COUNTIF($C$2:$C90,模板!$E$2) | C90: =IFERROR(VLOOKUP(K90,开票信息!$A:$C,3,0),"") | D90: Lycocelle绽家四季繁花香氛洗衣液600ml（白兰花与栀子花）-方瓶 | F90: 13 | G90: =IFERROR(H90/F90,"") | H90: 234 | J90: 秋容 | K90: BMCLUB | L90: =COUNTIF($K$2:K90,$K90)
A91: 90 | B91: =COUNTIF($C$2:$C91,模板!$E$2) | C91: =IFERROR(VLOOKUP(K91,开票信息!$A:$C,3,0),"") | D91: Lycocelle绽家护衣留香珠（一杯鲜橙）180g | F91: 1 | G91: =IFERROR(H91/F91,"") | H91: 20 | J91: 秋容 | K91: BMCLUB | L91: =COUNTIF($K$2:K91,$K91)
... A156: 155 | B156: =COUNTIF($C$2:$C156,模板!$E$2) | C156: =IFERROR(VLOOKUP(K156,开票信息!$A:$C,3,0),"") | D156: 绽家香氛衣物小美盒-杏色款 | F156: 1 | G156: =IFERROR(H156/F156,"") | H156: 0 | J156: 秋容 | K156: BMCLUB | L156: =COUNTIF($K$2:K156,$K156)
A157: 156 | B157: =COUNTIF($C$2:$C157,模板!$E$2) | C157: BMCLUB（后台提现） | D157: Lycocelle绽家蓝桉叶三合一洗衣凝珠（忍冬与铃兰）12g*10颗 | F157: 7 | G157: =IFERROR(H157/F157,"") | H157: 56 | J157: 秋容 | K157: BMCLUB（后台提现） | L157: =COUNTIF($K$2:K157,$K157)
A158: 157 | B158: =COUNTIF($C$2:$C158,模板!$E$2) | C158: BMCLUB（后台提现） | D158: Lycocelle绽家香樟木条5根装（含收纳袋） | F158: 3 | G158: =IFERROR(H158/F158,"") | H158: 24 | J158: 秋容 | K158: BMCLUB（后台提现） | L158: =COUNTIF($K$2:K158,$K158)
A159: 158 | B159: =COUNTIF($C$2:$C159,模板!$E$2) | C159: BMCLUB（后台提现） | D159: Lycocelle绽家马赛皂洗碗液750ml-长嘴泵头（金） | F159: 41 | G159: =IFERROR(H159/F159,"") | H159: 0 | J159: 秋容 | K159: BMCLUB（后台提现） | L159: =COUNTIF($K$2:K159,$K159)
A160: 159 | B160: =COUNTIF($C$2:$C160,模板!$E$2) | C160: BMCLUB（后台提现） | D160: 绽家×亲密的奥黛丽·赫本香水油香氛洗衣凝珠40颗桶装（金钱桔/金橙与檀木鸢尾） | F160: 2 | G160: =IFERROR(H160/F160,"") | H160: 120 | J160: 秋容 | K160: BMCLUB（后台提现） | L160: =COUNTIF($K$2:K160,$K160)
A161: 160 | B161: =COUNTIF($C$2:$C161,模板!$E$2) | C161: BMCLUB（后台提现） | D161: 绽家×亲密的奥黛丽·赫本香水油香氛洗衣凝珠40颗桶装（金钱桔与檀木鸢尾） | F161: 1 | G161: =IFERROR(H161/F161,"") | H161: 60 | J161: 秋容 | K161: BMCLUB（后台提现） | L161: =COUNTIF($K$2:K161,$K161)
A162: 161 | B162: =COUNTIF($C$2:$C162,模板!$E$2) | C162: BMCLUB（后台提现） | D162: 绽家×亲密的奥黛丽·赫本香水油香氛洗衣凝珠40颗桶装（青柚与檀木鸢尾） | F162: 1 | G162: =IFERROR(H162/F162,"") | H162: 60 | J162: 秋容 | K162: BMCLUB（后台提现） | L162: =COUNTIF($K$2:K162,$K162)
A163: 162 | B163: =COUNTIF($C$2:$C163,模板!$E$2) | C163: BMCLUB（后台提现） | D163: 绽家×亲密的奥黛丽·赫本香水油香氛洗衣凝珠6颗袋装（青柚与檀木鸢尾） | F163: 5 | G163: =IFERROR(H163/F163,"") | H163: 0 | J163: 秋容 | K163: BMCLUB（后台提现） | L163: =COUNTIF($K$2:K163,$K163)
A164: 163 | B164: =COUNTIF($C$2:$C164,模板!$E$2) | C164: BMCLUB（后台提现） | D164: 绽家四季繁花酵素香氛洗衣液90ml（甜橙与翡翠百里香） | F164: 1 | G164: =IFERROR(H164/F164,"") | H164: 7 | J164: 秋容 | K164: BMCLUB（后台提现） | L164: =COUNTIF($K$2:K164,$K164)
A165: 164 | B165: =COUNTIF($C$2:$C165,模板!$E$2) | C165: BMCLUB（后台提现） | D165: 绽家四季繁花酵素香氛洗衣液90ml（迈索尔檀木与小花茉莉） | F165: 4 | G165: =IFERROR(H165/F165,"") | H165: 28 | J165: 秋容 | K165: BMCLUB（后台提现） | L165: =COUNTIF($K$2:K165,$K165)
A166: 165 | B166: =COUNTIF($C$2:$C166,模板!$E$2) | C166: BMCLUB（后台提现） | D166: 绽家四季繁花香氛衣物柔顺剂120ml（白兰花与栀子花）-袋装 120ml | F166: 2 | G166: =IFERROR(H166/F166,"") | H166: 12 | J166: 秋容 | K166: BMCLUB（后台提现） | L166: =COUNTIF($K$2:K166,$K166)
A167: 166 | B167: =COUNTIF($C$2:$C167,模板!$E$2) | C167: BMCLUB（后台提现） | D167: 绽家多用途海绵清洁擦（单个） | F167: 9 | G167: =IFERROR(H167/F167,"") | H167: 18 | J167: 秋容 | K167: BMCLUB（后台提现） | L167: =COUNTIF($K$2:K167,$K167)
A168: 167 | B168: =COUNTIF($C$2:$C168,模板!$E$2) | C168: BMCLUB（后台提现） | D168: 绽家多用途香氛球（三秋桂子）-6颗装 | F168: 2 | G168: =IFERROR(H168/F168,"") | H168: 29 | J168: 秋容 | K168: BMCLUB（后台提现） | L168: =COUNTIF($K$2:K168,$K168)
... A177: 176 | B177: =COUNTIF($C$2:$C177,模板!$E$2) | C177: BMCLUB（后台提现） | D177: 赫本凝珠桶碎晶链 | F177: 1 | G177: =IFERROR(H177/F177,"") | H177: 0 | J177: 秋容 | K177: BMCLUB（后台提现） | L177: =COUNTIF($K$2:K177,$K177)
A178: 177 | B178: =COUNTIF($C$2:$C178,模板!$E$2) | C178: =IFERROR(VLOOKUP(K178,开票信息!$A:$C,3,0),"") | D178: Lycocelle绽家内衣洗衣液200ml (玫瑰) | F178: 3 | G178: =IFERROR(H178/F178,"") | H178: 45 | J178: 彭珠 | K178: Dora麻麻 | L178: =COUNTIF($K$2:K178,$K178)
A179: 178 | B179: =COUNTIF($C$2:$C179,模板!$E$2) | C179: =IFERROR(VLOOKUP(K179,开票信息!$A:$C,3,0),"") | D179: Lycocelle绽家内衣洗衣液200ml (经典) | F179: 3 | G179: =IFERROR(H179/F179,"") | H179: 45 | J179: 彭珠 | K179: Dora麻麻 | L179: =COUNTIF($K$2:K179,$K179)
A180: 179 | B180: =COUNTIF($C$2:$C180,模板!$E$2) | C180: =IFERROR(VLOOKUP(K180,开票信息!$A:$C,3,0),"") | D180: Lycocelle绽家内衣洗衣液330ml（玫瑰与蔷薇） | F180: 3 | G180: =IFERROR(H180/F180,"") | H180: 75 | J180: 彭珠 | K180: Dora麻麻 | L180: =COUNTIF($K$2:K180,$K180)
A181: 180 | B181: =COUNTIF($C$2:$C181,模板!$E$2) | C181: =IFERROR(VLOOKUP(K181,开票信息!$A:$C,3,0),"") | D181: Lycocelle绽家四季繁花酵素香氛洗衣液480ml（无花果与奶檀）-袋装 | F181: 9 | G181: =IFERROR(H181/F181,"") | H181: 0 | J181: 彭珠 | K181: Dora麻麻 | L181: =COUNTIF($K$2:K181,$K181)
A182: 181 | B182: =COUNTIF($C$2:$C182,模板!$E$2) | C182: =IFERROR(VLOOKUP(K182,开票信息!$A:$C,3,0),"") | D182: Lycocelle绽家四季繁花酵素香氛洗衣液480ml（甜橙与百里香）-袋装 | F182: 7 | G182: =IFERROR(H182/F182,"") | H182: 0 | J182: 彭珠 | K182: Dora麻麻 | L182: =COUNTIF($K$2:K182,$K182)
A183: 182 | B183: =COUNTIF($C$2:$C183,模板!$E$2) | C183: =IFERROR(VLOOKUP(K183,开票信息!$A:$C,3,0),"") | D183: Lycocelle绽家四季繁花酵素香氛洗衣液600ml（无花果与奶檀）-方瓶 | F183: 3 | G183: =IFERROR(H183/F183,"") | H183: 96 | J183: 彭珠 | K183: Dora麻麻 | L183: =COUNTIF($K$2:K183,$K183)
A184: 183 | B184: =COUNTIF($C$2:$C184,模板!$E$2) | C184: =IFERROR(VLOOKUP(K184,开票信息!$A:$C,3,0),"") | D184: Lycocelle绽家四季繁花酵素香氛洗衣液600ml（杏仁奶檀）-方瓶 | F184: 1 | G184: =IFERROR(H184/F184,"") | H184: 32 | J184: 彭珠 | K184: Dora麻麻 | L184: =COUNTIF($K$2:K184,$K184)
A185: 184 | B185: =COUNTIF($C$2:$C185,模板!$E$2) | C185: =IFERROR(VLOOKUP(K185,开票信息!$A:$C,3,0),"") | D185: Lycocelle绽家四季繁花香氛洗衣液600ml（白兰花与栀子花）-方瓶 | F185: 3 | G185: =IFERROR(H185/F185,"") | H185: 112 | J185: 彭珠 | K185: Dora麻麻 | L185: =COUNTIF($K$2:K185,$K185)
A186: 185 | B186: =COUNTIF($C$2:$C186,模板!$E$2) | C186: =IFERROR(VLOOKUP(K186,开票信息!$A:$C,3,0),"") | D186: Lycocelle绽家护衣留香珠（一杯鲜橙）180g（袋装） | F186: 1 | G186: =IFERROR(H186/F186,"") | H186: 0 | J186: 彭珠 | K186: Dora麻麻 | L186: =COUNTIF($K$2:K186,$K186)
A187: 186 | B187: =COUNTIF($C$2:$C187,模板!$E$2) | C187: =IFERROR(VLOOKUP(K187,开票信息!$A:$C,3,0),"") | D187: Lycocelle绽家护衣留香珠（一杯鲜橙）180g（铁盒版） | F187: 1 | G187: =IFERROR(H187/F187,"") | H187: 49 | J187: 彭珠 | K187: Dora麻麻 | L187: =COUNTIF($K$2:K187,$K187)
A188: 187 | B188: =COUNTIF($C$2:$C188,模板!$E$2) | C188: =IFERROR(VLOOKUP(K188,开票信息!$A:$C,3,0),"") | D188: Lycocelle绽家护衣留香珠（梨与小苍兰）180g（袋装） | F188: 1 | G188: =IFERROR(H188/F188,"") | H188: 24 | J188: 彭珠 | K188: Dora麻麻 | L188: =COUNTIF($K$2:K188,$K188)
A189: 188 | B189: =COUNTIF($C$2:$C189,模板!$E$2) | C189: =IFERROR(VLOOKUP(K189,开票信息!$A:$C,3,0),"") | D189: Lycocelle绽家蓝桉叶三合一洗衣凝珠（忍冬与铃兰）12g*10颗 | F189: 21 | G189: =IFERROR(H189/F189,"") | H189: 160 | J189: 彭珠 | K189: Dora麻麻 | L189: =COUNTIF($K$2:K189,$K189)
... A279: 278 | B279: =COUNTIF($C$2:$C279,模板!$E$2) | C279: =IFERROR(VLOOKUP(K279,开票信息!$A:$C,3,0),"") | D279: 绽家香水油浓缩洗衣液（雨后檀木鸢尾花）800mL-联名版 | F279: 1 | G279: =IFERROR(H279/F279,"") | H279: 49 | J279: 彭珠 | K279: Dora麻麻 | L279: =COUNTIF($K$2:K279,$K279)
A280: 279 | B280: =COUNTIF($C$2:$C280,模板!$E$2) | C280: Echo | D280: Lycocelle绽家内衣洗衣液100ml（经典） | F280: 50 | G280: =IFERROR(H280/F280,"") | H280: 0 | J280: 彭珠 | K280: Echo | L280: =COUNTIF($K$2:K280,$K280)
A281: 280 | B281: =COUNTIF($C$2:$C281,模板!$E$2) | C281: Echo | D281: Lycocelle绽家内衣洗衣液200ml (玫瑰) | F281: 4 | G281: =IFERROR(H281/F281,"") | H281: 57.5 | J281: 彭珠 | K281: Echo | L281: =COUNTIF($K$2:K281,$K281)
A282: 281 | B282: =COUNTIF($C$2:$C282,模板!$E$2) | C282: Echo | D282: Lycocelle绽家内衣洗衣液200ml (经典) | F282: 8 | G282: =IFERROR(H282/F282,"") | H282: 113.5 | J282: 彭珠 | K282: Echo | L282: =COUNTIF($K$2:K282,$K282)
A283: 282 | B283: =COUNTIF($C$2:$C283,模板!$E$2) | C283: Echo | D283: Lycocelle绽家内衣洗衣液330ml（七月炉火） | F283: 5 | G283: =IFERROR(H283/F283,"") | H283: 140 | J283: 彭珠 | K283: Echo | L283: =COUNTIF($K$2:K283,$K283)
A284: 283 | B284: =COUNTIF($C$2:$C284,模板!$E$2) | C284: Echo | D284: Lycocelle绽家内衣洗衣液330ml（爱丽斯梦境） | F284: 2 | G284: =IFERROR(H284/F284,"") | H284: 56 | J284: 彭珠 | K284: Echo | L284: =COUNTIF($K$2:K284,$K284)
A285: 284 | B285: =COUNTIF($C$2:$C285,模板!$E$2) | C285: Echo | D285: Lycocelle绽家内衣洗衣液330ml（玫瑰与蔷薇） | F285: 6 | G285: =IFERROR(H285/F285,"") | H285: 168 | J285: 彭珠 | K285: Echo | L285: =COUNTIF($K$2:K285,$K285)
A286: 285 | B286: =COUNTIF($C$2:$C286,模板!$E$2) | C286: Echo | D286: Lycocelle绽家内衣洗衣液330ml（粉红葡萄柚） | F286: 9 | G286: =IFERROR(H286/F286,"") | H286: 252 | J286: 彭珠 | K286: Echo | L286: =COUNTIF($K$2:K286,$K286)
A287: 286 | B287: =COUNTIF($C$2:$C287,模板!$E$2) | C287: Echo | D287: Lycocelle绽家内衣洗衣液330ml（经典） | F287: 6 | G287: =IFERROR(H287/F287,"") | H287: 168 | J287: 彭珠 | K287: Echo | L287: =COUNTIF($K$2:K287,$K287)
A288: 287 | B288: =COUNTIF($C$2:$C288,模板!$E$2) | C288: Echo | D288: Lycocelle绽家四季繁花酵素香氛洗衣液480ml（无花果与奶檀）-袋装 | F288: 12 | G288: =IFERROR(H288/F288,"") | H288: 0 | J288: 彭珠 | K288: Echo | L288: =COUNTIF($K$2:K288,$K288)
A289: 288 | B289: =COUNTIF($C$2:$C289,模板!$E$2) | C289: Echo | D289: Lycocelle绽家四季繁花酵素香氛洗衣液480ml（甜橙与百里香）-袋装 | F289: 17 | G289: =IFERROR(H289/F289,"") | H289: 0 | J289: 彭珠 | K289: Echo | L289: =COUNTIF($K$2:K289,$K289)
A290: 289 | B290: =COUNTIF($C$2:$C290,模板!$E$2) | C290: Echo | D290: Lycocelle绽家四季繁花酵素香氛洗衣液（迈索尔檀木与小花茉莉）30ml | F290: 2 | G290: =IFERROR(H290/F290,"") | H290: 0 | J290: 彭珠 | K290: Echo | L290: =COUNTIF($K$2:K290,$K290)
A291: 290 | B291: =COUNTIF($C$2:$C291,模板!$E$2) | C291: Echo | D291: Lycocelle绽家四季繁花香氛洗衣液600ml（白兰花与栀子花）-方瓶 | F291: 3 | G291: =IFERROR(H291/F291,"") | H291: 118.5 | J291: 彭珠 | K291: Echo | L291: =COUNTIF($K$2:K291,$K291)
... A583: 582 | B583: =COUNTIF($C$2:$C583,模板!$E$2) | C583: MOMO SHOP | D583: 绽家香水油浓缩洗衣液（落木十日檀）30mL-袋装-联名版 | F583: 14 | G583: =IFERROR(H583/F583,"") | H583: 0 | J583: 彭珠 | K583: MOMO SHOP | L583: =COUNTIF($K$2:K583,$K583)
A584: 583 | B584: =COUNTIF($C$2:$C584,模板!$E$2) | C584: =IFERROR(VLOOKUP(K584,开票信息!$A:$C,3,0),"") | D584: Lycocelle绽家亚麻衣物洗衣液500ml（忍冬铃兰） | F584: 1 | G584: =IFERROR(H584/F584,"") | H584: 34 | J584: 彭珠 | K584: Memore | L584: =COUNTIF($K$2:K584,$K584)
A585: 584 | B585: =COUNTIF($C$2:$C585,模板!$E$2) | C585: =IFERROR(VLOOKUP(K585,开票信息!$A:$C,3,0),"") | D585: Lycocelle绽家内衣洗衣液100ml（经典） | F585: 8 | G585: =IFERROR(H585/F585,"") | H585: 0 | J585: 彭珠 | K585: Memore | L585: =COUNTIF($K$2:K585,$K585)
A586: 585 | B586: =COUNTIF($C$2:$C586,模板!$E$2) | C586: =IFERROR(VLOOKUP(K586,开票信息!$A:$C,3,0),"") | D586: Lycocelle绽家内衣洗衣液200ml (玫瑰) | F586: 15 | G586: =IFERROR(H586/F586,"") | H586: 210 | J586: 彭珠 | K586: Memore | L586: =COUNTIF($K$2:K586,$K586)
A587: 586 | B587: =COUNTIF($C$2:$C587,模板!$E$2) | C587: =IFERROR(VLOOKUP(K587,开票信息!$A:$C,3,0),"") | D587: Lycocelle绽家内衣洗衣液200ml (经典) | F587: 13 | G587: =IFERROR(H587/F587,"") | H587: 182 | J587: 彭珠 | K587: Memore | L587: =COUNTIF($K$2:K587,$K587)
A588: 587 | B588: =COUNTIF($C$2:$C588,模板!$E$2) | C588: =IFERROR(VLOOKUP(K588,开票信息!$A:$C,3,0),"") | D588: Lycocelle绽家内衣洗衣液330ml（七月炉火） | F588: 26 | G588: =IFERROR(H588/F588,"") | H588: 650 | J588: 彭珠 | K588: Memore | L588: =COUNTIF($K$2:K588,$K588)
A589: 588 | B589: =COUNTIF($C$2:$C589,模板!$E$2) | C589: =IFERROR(VLOOKUP(K589,开票信息!$A:$C,3,0),"") | D589: Lycocelle绽家内衣洗衣液330ml（爱丽斯梦境） | F589: 34 | G589: =IFERROR(H589/F589,"") | H589: 850 | J589: 彭珠 | K589: Memore | L589: =COUNTIF($K$2:K589,$K589)
A590: 589 | B590: =COUNTIF($C$2:$C590,模板!$E$2) | C590: =IFERROR(VLOOKUP(K590,开票信息!$A:$C,3,0),"") | D590: Lycocelle绽家内衣洗衣液330ml（玫瑰与蔷薇） | F590: 42 | G590: =IFERROR(H590/F590,"") | H590: 1050 | J590: 彭珠 | K590: Memore | L590: =COUNTIF($K$2:K590,$K590)
A591: 590 | B591: =COUNTIF($C$2:$C591,模板!$E$2) | C591: =IFERROR(VLOOKUP(K591,开票信息!$A:$C,3,0),"") | D591: Lycocelle绽家内衣洗衣液330ml（粉红葡萄柚） | F591: 37 | G591: =IFERROR(H591/F591,"") | H591: 925 | J591: 彭珠 | K591: Memore | L591: =COUNTIF($K$2:K591,$K591)
A592: 591 | B592: =COUNTIF($C$2:$C592,模板!$E$2) | C592: =IFERROR(VLOOKUP(K592,开票信息!$A:$C,3,0),"") | D592: Lycocelle绽家内衣洗衣液330ml（经典） | F592: 66 | G592: =IFERROR(H592/F592,"") | H592: 1650 | J592: 彭珠 | K592: Memore | L592: =COUNTIF($K$2:K592,$K592)
A593: 592 | B593: =COUNTIF($C$2:$C593,模板!$E$2) | C593: =IFERROR(VLOOKUP(K593,开票信息!$A:$C,3,0),"") | D593: Lycocelle绽家四季繁花酵素香氛洗衣液480ml（无花果与奶檀）-袋装 | F593: 28 | G593: =IFERROR(H593/F593,"") | H593: 0 | J593: 彭珠 | K593: Memore | L593: =COUNTIF($K$2:K593,$K593)
A594: 593 | B594: =COUNTIF($C$2:$C594,模板!$E$2) | C594: =IFERROR(VLOOKUP(K594,开票信息!$A:$C,3,0),"") | D594: Lycocelle绽家四季繁花酵素香氛洗衣液480ml（甜橙与百里香）-袋装 | F594: 20 | G594: =IFERROR(H594/F594,"") | H594: 0 | J594: 彭珠 | K594: Memore | L594: =COUNTIF($K$2:K594,$K594)
A595: 594 | B595: =COUNTIF($C$2:$C595,模板!$E$2) | C595: =IFERROR(VLOOKUP(K595,开票信息!$A:$C,3,0),"") | D595: Lycocelle绽家四季繁花酵素香氛洗衣液480ml（迈索尔檀木与小花茉莉）-袋装 | F595: 1 | G595: =IFERROR(H595/F595,"") | H595: 0 | J595: 彭珠 | K595: Memore | L595: =COUNTIF($K$2:K595,$K595)
... A783: 782 | B783: =COUNTIF($C$2:$C783,模板!$E$2) | C783: =IFERROR(VLOOKUP(K783,开票信息!$A:$C,3,0),"") | D783: 赫本凝珠桶碎晶链 | F783: 3 | G783: =IFERROR(H783/F783,"") | H783: 0 | J783: 彭珠 | K783: Memore | L783: =COUNTIF($K$2:K783,$K783)
A784: 783 | B784: =COUNTIF($C$2:$C784,模板!$E$2) | C784: NN精选 | D784: Lycocelle绽家内衣洗衣液200ml (玫瑰) | F784: 1 | G784: =IFERROR(H784/F784,"") | H784: 14 | J784: 秋容 | K784: NN精选 | L784: =COUNTIF($K$2:K784,$K784)
A785: 784 | B785: =COUNTIF($C$2:$C785,模板!$E$2) | C785: NN精选 | D785: Lycocelle绽家内衣洗衣液200ml (经典) | F785: 2 | G785: =IFERROR(H785/F785,"") | H785: 28 | J785: 秋容 | K785: NN精选 | L785: =COUNTIF($K$2:K785,$K785)
A786: 785 | B786: =COUNTIF($C$2:$C786,模板!$E$2) | C786: NN精选 | D786: Lycocelle绽家蓝桉叶精油地板水500ml（甜橙与百里香） | F786: 2 | G786: =IFERROR(H786/F786,"") | H786: 44 | J786: 秋容 | K786: NN精选 | L786: =COUNTIF($K$2:K786,$K786)
A787: 786 | B787: =COUNTIF($C$2:$C787,模板!$E$2) | C787: NN精选 | D787: Lycocelle绽家蓝桉叶精油地板水500ml（茉莉与栀子花） | F787: 1 | G787: =IFERROR(H787/F787,"") | H787: 20 | J787: 秋容 | K787: NN精选 | L787: =COUNTIF($K$2:K787,$K787)
A788: 787 | B788: =COUNTIF($C$2:$C788,模板!$E$2) | C788: NN精选 | D788: Lycocelle绽家蓝桉叶精油地板水500ml（葡萄柚与琥珀） | F788: 1 | G788: =IFERROR(H788/F788,"") | H788: 20 | J788: 秋容 | K788: NN精选 | L788: =COUNTIF($K$2:K788,$K788)
A789: 788 | B789: =COUNTIF($C$2:$C789,模板!$E$2) | C789: NN精选 | D789: 绽家×奥黛丽赫本小黑裙香氛洗衣液1700ml（经典小黑裙）（香草茉莉与晚香玉）-特 | F789: 7 | G789: =IFERROR(H789/F789,"") | H789: 280 | J789: 秋容 | K789: NN精选 | L789: =COUNTIF($K$2:K789,$K789)
A790: 789 | B790: =COUNTIF($C$2:$C790,模板!$E$2) | C790: NN精选 | D790: 绽家×奥黛丽赫本小黑裙香氛洗衣液1700ml（花瓣舞裙）（黑琥珀与橡木玫瑰）-特 | F790: 4 | G790: =IFERROR(H790/F790,"") | H790: 160 | J790: 秋容 | K790: NN精选 | L790: =COUNTIF($K$2:K790,$K790)
A791: 790 | B791: =COUNTIF($C$2:$C791,模板!$E$2) | C791: NN精选 | D791: 绽家一滴除臭香氛精油套组 20g*3 | F791: 5 | G791: =IFERROR(H791/F791,"") | H791: 160 | J791: 秋容 | K791: NN精选 | L791: =COUNTIF($K$2:K791,$K791)
A792: 791 | B792: =COUNTIF($C$2:$C792,模板!$E$2) | C792: NN精选 | D792: 绽家内衣洗衣液200ml(飞舞樱花与乳檀木) | F792: 2 | G792: =IFERROR(H792/F792,"") | H792: 28 | J792: 秋容 | K792: NN精选 | L792: =COUNTIF($K$2:K792,$K792)
A793: 792 | B793: =COUNTIF($C$2:$C793,模板!$E$2) | C793: NN精选 | D793: 绽家内衣洗衣液200ml（檀木与小花茉莉） | F793: 1 | G793: =IFERROR(H793/F793,"") | H793: 14 | J793: 秋容 | K793: NN精选 | L793: =COUNTIF($K$2:K793,$K793)
A794: 793 | B794: =COUNTIF($C$2:$C794,模板!$E$2) | C794: NN精选 | D794: 绽家内衣洗衣液200ml（葡萄柚与橙花） | F794: 2 | G794: =IFERROR(H794/F794,"") | H794: 28 | J794: 秋容 | K794: NN精选 | L794: =COUNTIF($K$2:K794,$K794)
A795: 794 | B795: =COUNTIF($C$2:$C795,模板!$E$2) | C795: NN精选 | D795: 绽家精油香薰片(飞舞樱花与乳檀木) | F795: 6 | G795: =IFERROR(H795/F795,"") | H795: 15 | J795: 秋容 | K795: NN精选 | L795: =COUNTIF($K$2:K795,$K795)
... A801: 800 | B801: =COUNTIF($C$2:$C801,模板!$E$2) | C801: Nice好物集 | D801: Lycocelle绽家四季繁花酵素香氛洗衣液600ml（无花果与奶檀）-方瓶 | F801: 2 | G801: =IFERROR(H801/F801,"") | H801: 26 | J801: 秋容 | K801: Nice好物集 | L801: =COUNTIF($K$2:K801,$K801)
A802: 801 | B802: =COUNTIF($C$2:$C802,模板!$E$2) | C802: None | D802: None | F802: 0 | G802: =IFERROR(H802/F802,"") | H802: 0 | K802: None | L802: =COUNTIF($K$2:K802,$K802)
A803: 802 | B803: =COUNTIF($C$2:$C803,模板!$E$2) | C803: P妈 | D803: Lycocelle绽家四季繁花酵素香氛洗衣液480ml（无花果与奶檀）-袋装 | F803: 153 | G803: =IFERROR(H803/F803,"") | H803: 0 | J803: 加丽 | K803: P妈 | L803: =COUNTIF($K$2:K803,$K803)
A804: 803 | B804: =COUNTIF($C$2:$C804,模板!$E$2) | C804: P妈 | D804: Lycocelle绽家四季繁花酵素香氛洗衣液480ml（甜橙与百里香）-袋装 | F804: 111 | G804: =IFERROR(H804/F804,"") | H804: 0 | J804: 加丽 | K804: P妈 | L804: =COUNTIF($K$2:K804,$K804)
A805: 804 | B805: =COUNTIF($C$2:$C805,模板!$E$2) | C805: P妈 | D805: Lycocelle绽家四季繁花酵素香氛洗衣液480ml（迈索尔檀木与小花茉莉）-袋装 | F805: 17 | G805: =IFERROR(H805/F805,"") | H805: 0 | J805: 加丽 | K805: P妈 | L805: =COUNTIF($K$2:K805,$K805)
A806: 805 | B806: =COUNTIF($C$2:$C806,模板!$E$2) | C806: P妈 | D806: Lycocelle绽家四季繁花酵素香氛洗衣液600ml（无花果与奶檀）-方瓶 | F806: 8 | G806: =IFERROR(H806/F806,"") | H806: 328 | J806: 加丽 | K806: P妈 | L806: =COUNTIF($K$2:K806,$K806)
A807: 806 | B807: =COUNTIF($C$2:$C807,模板!$E$2) | C807: P妈 | D807: Lycocelle绽家四季繁花香氛洗衣液600ml（白兰花与栀子花）-方瓶 | F807: 55 | G807: =IFERROR(H807/F807,"") | H807: 2255 | J807: 加丽 | K807: P妈 | L807: =COUNTIF($K$2:K807,$K807)
A808: 807 | B808: =COUNTIF($C$2:$C808,模板!$E$2) | C808: P妈 | D808: Lycocelle绽家蓝桉叶三合一洗衣凝珠（忍冬与铃兰）12g*10颗 | F808: 37 | G808: =IFERROR(H808/F808,"") | H808: 296 | J808: 加丽 | K808: P妈 | L808: =COUNTIF($K$2:K808,$K808)
...
